setup.cfg
setup.py
firstdata/__init__.py
firstdata/tests.py
firstdata.egg-info/PKG-INFO
firstdata.egg-info/SOURCES.txt
firstdata.egg-info/dependency_links.txt
firstdata.egg-info/requires.txt
firstdata.egg-info/top_level.txt
firstdata.egg-info/zip-safe