Metadata-Version: 1.0
Name: firstdata
Version: 0.9
Summary: Unofficial First Data G4 Handlers
Home-page: https://github.com/stevepeak/firstdata
Author: @iopeak
Author-email: steve@stevepeak.net
License: http://www.apache.org/licenses/LICENSE-2.0
Keywords: firstdata gateway credit creditcard g4 processing
Platform: UNKNOWN
Classifier: Development Status :: 5 - Production/Stable
Classifier: Intended Audience :: Developers
Classifier: License :: OSI Approved :: Apache Software License
Classifier: Programming Language :: Python
Classifier: Programming Language :: Python :: 2
Classifier: Programming Language :: Python :: 3
Classifier: Programming Language :: Python :: Implementation :: PyPy
Classifier: Topic :: Office/Business :: Financial
